smalldataviewer/__init__.py
smalldataviewer/__main__.py
smalldataviewer/ext.py
smalldataviewer/files.py
smalldataviewer/version.py
smalldataviewer/viewer.py
smalldataviewer-0.10.0.dist-info/LICENSE
smalldataviewer-0.10.0.dist-info/METADATA
smalldataviewer-0.10.0.dist-info/WHEEL
smalldataviewer-0.10.0.dist-info/entry_points.txt
smalldataviewer-0.10.0.dist-info/top_level.txt
smalldataviewer-0.10.0.dist-info/RECORD
