Metadata-Version: 2.1
Name: smalldataviewer
Version: 0.10.0
Summary: Command-line tool and python library for visualising small 3D datasets
Home-page: https://github.com/clbarnes/smalldataviewer
Author: Chris L Barnes
Author-email: barnesc@janelia.hhmi.org
License: MIT
Keywords: image volume 3d hdf5 n5 zarr
Platform: UNKNOWN
Classifier: Development Status :: 4 - Beta
Classifier: License :: OSI Approved :: MIT License
Classifier: Programming Language :: Python
Classifier: Programming Language :: Python :: 3.7
Classifier: Programming Language :: Python :: 3.6
Requires-Python: >=3.6.*
Requires-Dist: numpy (>=1.7.1)
Requires-Dist: matplotlib (>=3.0)
Requires-Dist: mpl-colors
Provides-Extra: all
Requires-Dist: h5py (>=2.0) ; extra == 'all'
Requires-Dist: imageio (>=2.3) ; extra == 'all'
Requires-Dist: imageio[fits] (>=2.3) ; extra == 'all'
Requires-Dist: imageio[itk] (>=2.3) ; extra == 'all'
Provides-Extra: fits
Requires-Dist: imageio[fits] (>=2.3) ; extra == 'fits'
Provides-Extra: hdf5
Requires-Dist: h5py (>=2.0) ; extra == 'hdf5'
Provides-Extra: img
Requires-Dist: imageio (>=2.3) ; extra == 'img'
Provides-Extra: itk
Requires-Dist: imageio[itk] (>=2.3) ; extra == 'itk'
